odoo10_addon_website_sale_select_qty-10.0.1.0.0-py2.7-nspkg.pth
odoo/addons/website_sale_select_qty/README.rst
odoo/addons/website_sale_select_qty/__init__.py
odoo/addons/website_sale_select_qty/__manifest__.py
odoo/addons/website_sale_select_qty/controllers/__init__.py
odoo/addons/website_sale_select_qty/controllers/main.py
odoo/addons/website_sale_select_qty/static/description/icon.png
odoo/addons/website_sale_select_qty/static/src/xml/website_sale_select_qty.xml
odoo/addons/website_sale_select_qty/tests/__init__.py
odoo/addons/website_sale_select_qty/tests/test_main.py
odoo10_addon_website_sale_select_qty-10.0.1.0.0.dist-info/DESCRIPTION.rst
odoo10_addon_website_sale_select_qty-10.0.1.0.0.dist-info/METADATA
odoo10_addon_website_sale_select_qty-10.0.1.0.0.dist-info/RECORD
odoo10_addon_website_sale_select_qty-10.0.1.0.0.dist-info/WHEEL
odoo10_addon_website_sale_select_qty-10.0.1.0.0.dist-info/metadata.json
odoo10_addon_website_sale_select_qty-10.0.1.0.0.dist-info/namespace_packages.txt
odoo10_addon_website_sale_select_qty-10.0.1.0.0.dist-info/top_level.txt
